RandomPokemon/RandomPokemonLibrary.py
RandomPokemon/__init__.py
RandomPokemonLibrary-1.0.1.dist-info/METADATA
RandomPokemonLibrary-1.0.1.dist-info/WHEEL
RandomPokemonLibrary-1.0.1.dist-info/top_level.txt
RandomPokemonLibrary-1.0.1.dist-info/RECORD
