Metadata-Version: 2.1
Name: RandomPokemonLibrary
Version: 1.0.1
Summary: Una biblioteca que contiene la clase RandomPokemon
Author: Martha Morales
Author-email: martha_morales@live.com.mx
Requires-Dist: pandas
